dash/__init__.py
dash/dash/__init__.py
dash/dash/all.hy
dash/dash/cons.hy
dash/dash/dash.hy
dash/dash/polyfill.hy
dash/lodash.hy
dash/misc.hy
dash/operator.hy
dash/strtools.hy
dash_hy-0.1.0.dist-info/METADATA
dash_hy-0.1.0.dist-info/WHEEL
dash_hy-0.1.0.dist-info/RECORD
