Metadata-Version: 2.1
Name: dash-hy
Version: 0.1.0
Summary: A modern list library for Hy
Author: vhqr0
Author-email: zq_cmd@163.com
Requires-Python: >=3.12,<3.13
Classifier: Programming Language :: Python :: 3
Classifier: Programming Language :: Python :: 3.12
Requires-Dist: hy (>=0.28.0,<0.29.0)
